sicsearch/__init__.py
sicsearch/cardlist.py
sicsearch/cardpanel.py
sicsearch/database.py
sicsearch/fzmatch.py
sicsearch/search.py
sicsearch/suppress.py
sicsearch/version.py
sicsearch/watcher.py
sicsearch-0.2.2a1.dist-info/LICENSE
sicsearch-0.2.2a1.dist-info/METADATA
sicsearch-0.2.2a1.dist-info/WHEEL
sicsearch-0.2.2a1.dist-info/entry_points.txt
sicsearch-0.2.2a1.dist-info/top_level.txt
sicsearch-0.2.2a1.dist-info/zip-safe
sicsearch-0.2.2a1.dist-info/RECORD
