Metadata-Version: 2.1
Name: sicsearch
Version: 0.2.2a1
Summary: Safe in Cloud DB Search
Home-page: https://github.com/ironsigma/sicsearch
Author: Juan D Frias
Author-email: juandfrias@gmail.com
License: MIT
Download-URL: https://github.com/ironsigma/sicsearch/archive/v0.2.2-alpha.1.tar.gz
Keywords: SIC,SafeInCloud,Decryption,Password
Platform: UNKNOWN
Classifier: Development Status :: 3 - Alpha
Classifier: Environment :: Console :: Curses
Classifier: Intended Audience :: End Users/Desktop
Classifier: License :: OSI Approved :: MIT License
Classifier: Natural Language :: English
Classifier: Topic :: Security
Classifier: Topic :: Security :: Cryptography
Classifier: Topic :: Utilities
Classifier: Programming Language :: Python :: 3
Classifier: Programming Language :: Python :: 3 :: Only
Classifier: Programming Language :: Python :: 3.6
Classifier: Programming Language :: Python :: Implementation
Requires-Python: >=3.6
Requires-Dist: passlib
Requires-Dist: pyperclip
Requires-Dist: pycryptodome
